{
  "instance": {
    "info": {
      "author": "Zyneon Studios",
      "authors": [
        "Zyneon Studios"
      ],
      "description": "U(ltra) K(rasses) Z(yneon) P(rojekt)",
      "name": "UKZP (Lite)",
      "summary": "U(ltra) K(rasses) Z(yneon) P(rojekt)",
      "version": "2024.7"
    },
    "meta": {
      "description": "U(ltra) K(rasses) Z(yneon) P(rojekt)",
      "download": "https://www.dropbox.com/scl/fi/3wy6h81ds0h6kcigjfd6n/lite.zip?rlkey=m0n1pptir4ljb8c6i78va132i&dl=1",
      "forgeType": "NEW",
      "id": "official/ukzp-lite",
      "isEditable": false,
      "isHidden": false,
      "location": "https://zyneonstudios.github.io/nexus-nex/zyndex/instances/official/ukzp-lite.json",
      "origin": "https://zyneonstudios.github.io/nexus-nex/zyndex/index.json",
      "tags": [
        "minecraft-1.18.2",
        "modloder-forge"
      ]
    },
    "resources": {
      "background": "https://i.ibb.co/7W23k3M/ukzp-lite.webp",
      "icon": "https://i.ibb.co/YTq61wN/ukzp-lite.png",
      "logo": "https://i.ibb.co/Wz7ZW9K/ukzp-lite-logo.png",
      "thumbnail": "https://i.ibb.co/Scrsj2H/ukzp-lite.png"
    },
    "versions": {
      "forge": "40.2.17",
      "minecraft": "1.18.2"
    }
  },
  "scheme": "2024.7"
}